<?xml version="1.0" encoding="UTF-8"?>

<fontFamilies>

    <fontFamily name="SansSerif">
        <exportFonts>
            <export key="net.sf.jasperreports.html">Arial, Helvetica, sans-serif</export>
        </exportFonts>
    </fontFamily>

    <fontFamily name="Serif">
        <exportFonts>
            <export key="net.sf.jasperreports.html">'Times New Roman', Times, serif</export>
        </exportFonts>
    </fontFamily>

    <fontFamily name="Monospaced">
        <exportFonts>
            <export key="net.sf.jasperreports.html">'Courier New', Courier, monospace</export>
        </exportFonts>
    </fontFamily>

</fontFamilies>
